bibliopixel/VERSION
bibliopixel/__init__.py
bibliopixel/animation/__init__.py
bibliopixel/animation/adaptor.py
bibliopixel/animation/animation.py
bibliopixel/animation/animation_threading.py
bibliopixel/animation/circle.py
bibliopixel/animation/collection.py
bibliopixel/animation/cube.py
bibliopixel/animation/failed.py
bibliopixel/animation/feedback.py
bibliopixel/animation/fill.py
bibliopixel/animation/game.py
bibliopixel/animation/gif_writer.py
bibliopixel/animation/indexed.py
bibliopixel/animation/limiter.py
bibliopixel/animation/matrix.py
bibliopixel/animation/mixer.py
bibliopixel/animation/movie_writer.py
bibliopixel/animation/off.py
bibliopixel/animation/parallel.py
bibliopixel/animation/pov.py
bibliopixel/animation/receiver.py
bibliopixel/animation/runner.py
bibliopixel/animation/sequence.py
bibliopixel/animation/split.py
bibliopixel/animation/strip.py
bibliopixel/animation/tests.py
bibliopixel/animation/wrapper.py
bibliopixel/animation/remote/__init__.py
bibliopixel/animation/remote/control.py
bibliopixel/animation/remote/opener.py
bibliopixel/animation/remote/server.py
bibliopixel/animation/remote/trigger.py
bibliopixel/animation/remote/trigger_process.py
bibliopixel/animation/reprocess/__init__.py
bibliopixel/animation/reprocess/functions.py
bibliopixel/animation/reprocess/reprocess.py
bibliopixel/builder/__init__.py
bibliopixel/builder/builder.py
bibliopixel/builder/description.py
bibliopixel/builder/pixels.py
bibliopixel/builder/runner.py
bibliopixel/builder/saved_description.py
bibliopixel/builder/sections.py
bibliopixel/colors/__init__.py
bibliopixel/colors/arithmetic.py
bibliopixel/colors/classic.py
bibliopixel/colors/closest_colors.py
bibliopixel/colors/colors.py
bibliopixel/colors/conversions.py
bibliopixel/colors/gamma.py
bibliopixel/colors/juce.py
bibliopixel/colors/legacy_palette.py
bibliopixel/colors/make.py
bibliopixel/colors/names.py
bibliopixel/colors/palette.py
bibliopixel/colors/palettes.py
bibliopixel/colors/printer.py
leds-3.5.1.dist-info/LICENSE
leds-3.5.1.dist-info/METADATA
leds-3.5.1.dist-info/WHEEL
leds-3.5.1.dist-info/top_level.txt
leds-3.5.1.dist-info/RECORD
